MANIFEST.in
README.rst
requirements.txt
setup.cfg
setup.py
star_builder/__init__.py
star_builder/app.py
star_builder/helper.py
star_builder/route.py
star_builder.egg-info/PKG-INFO
star_builder.egg-info/SOURCES.txt
star_builder.egg-info/dependency_links.txt
star_builder.egg-info/entry_points.txt
star_builder.egg-info/requires.txt
star_builder.egg-info/top_level.txt
star_builder.egg-info/zip-safe
star_builder/bases/__init__.py
star_builder/bases/components.py
star_builder/bases/controller.py
star_builder/bases/entities.py
star_builder/bases/exceptions.py
star_builder/bases/hooks.py
star_builder/bases/manager.py
star_builder/bases/metas.py
star_builder/bases/model_factory.py
star_builder/bases/response.py
star_builder/bases/service.py
star_builder/bases/websocket.py
star_builder/build/__init__.py
star_builder/build/tasks.py
star_builder/console/__init__.py
star_builder/console/mocker.py
star_builder/pytest/__init__.py
star_builder/pytest/decorator.py
star_builder/solo/__init__.py
star_builder/solo/manager.py
star_builder/templates/model/${module_name}.py.tmpl
star_builder/templates/project/MANIFEST.in.tmpl
star_builder/templates/project/README.md.tmpl
star_builder/templates/project/README.rst.tmpl
star_builder/templates/project/requirements.txt.tmpl
star_builder/templates/project/setup.py.tmpl
star_builder/templates/project/${name}/__init__.py
star_builder/templates/project/${name}/settings.py.tmpl
star_builder/templates/project/${name}/tasks.py.tmpl
star_builder/templates/project/${name}/web_app.py.tmpl
star_builder/templates/project/${name}/${name}/__init__.py
star_builder/templates/project/${name}/__pycache__/__init__.cpython-36.pyc
star_builder/templates/service/__init__.py.tmpl
star_builder/templates/service/service.py.tmpl
star_builder/templates/solo/${back_trace}solo_app.py.tmpl
star_builder/templates/solo/__init__.py.tmpl
star_builder/types/__init__.py
star_builder/types/formats.py
star_builder/types/validators.py
test/test_array.py
test/test_bool.py
test/test_date_format.py
test/test_error_hook.py
test/test_file_stream.py
test/test_format.py
test/test_in.py
test/test_model.py
test/test_model_inject.py
test/test_proxy.py
test/test_service_inject.py
test/test_union.py
test/test_websocket.py