Metadata-Version: 1.1
Name: star-builder
Version: 0.9.16
Summary: enhance apistar web framework. 
Home-page: https://www.github.com/ShichaoMa/star_builder
Author: cn
Author-email: cnaafhvk@foxmail.com
License: MIT
Keywords: apistar
Platform: UNKNOWN
Classifier: License :: OSI Approved :: MIT License
Classifier: Programming Language :: Python :: 3.6
Classifier: Intended Audience :: Developers
Classifier: Operating System :: Unix
